{
  "annotations": {
    "list": [
      {
        "builtIn": 1,
        "datasource": {
          "type": "grafana",
          "uid": "-- Grafana --"
        },
        "enable": true,
        "hide": true,
        "iconColor": "rgba(0, 211, 255, 1)",
        "name": "Annotations & Alerts",
        "type": "dashboard"
      }
    ]
  },
  "description": "Dashboard for Aliyun bill total and product costs, with categorical month axis.",
  "editable": true,
  "fiscalYearStartMonth": 0,
  "graphTooltip": 0,
  "id": 0,
  "links": [],
  "panels": [
    {
      "datasource": {
        "type": "prometheus",
        "uid": "prometheus"
      },
      "fieldConfig": {
        "defaults": {
          "color": {
            "mode": "thresholds"
          },
          "mappings": [],
          "thresholds": {
            "mode": "absolute",
            "steps": [
              {
                "color": "green",
                "value": 0
              },
              {
                "color": "red",
                "value": 80
              }
            ]
          }
        },
        "overrides": []
      },
      "gridPos": {
        "h": 8,
        "w": 14,
        "x": 0,
        "y": 0
      },
      "id": 4,
      "options": {
        "minVizHeight": 75,
        "minVizWidth": 75,
        "orientation": "auto",
        "reduceOptions": {
          "calcs": [
            "lastNotNull"
          ],
          "fields": "",
          "values": false
        },
        "showThresholdLabels": false,
        "showThresholdMarkers": true,
        "sizing": "auto"
      },
      "pluginVersion": "12.2.1",
      "targets": [
        {
          "editorMode": "code",
          "expr": "sum by (month) (aliyun_bill_total_cost{account=~\"$account\",month=~\"$month\"})",
          "legendFormat": "{{month}}",
          "range": true,
          "refId": "A"
        }
      ],
      "title": "All Amount Of Every Month",
      "type": "gauge"
    },
    {
      "datasource": {
        "type": "prometheus",
        "uid": "prometheus"
      },
      "fieldConfig": {
        "defaults": {
          "color": {
            "mode": "palette-classic"
          },
          "custom": {
            "hideFrom": {
              "legend": false,
              "tooltip": false,
              "viz": false
            }
          },
          "decimals": 2,
          "mappings": [],
          "min": 0,
          "unit": "currencyUSD"
        },
        "overrides": [
          {
            "__systemRef": "hideSeriesFrom",
            "matcher": {
              "id": "byNames",
              "options": {
                "mode": "exclude",
                "names": [
                  "alikafka",
                  "cas",
                  "cbs",
                  "cdt",
                  "csk",
                  "dcdn",
                  "ddos",
                  "dms",
                  "dts",
                  "ecs",
                  "eip",
                  "flowpack",
                  "kvstore",
                  "mse",
                  "nas",
                  "nat",
                  "nat_gw",
                  "ons",
                  "oss",
                  "rds",
                  "redisa",
                  "sas",
                  "slb",
                  "sls",
                  "snapshot",
                  "supportplan_intl",
                  "waf"
                ],
                "prefix": "All except:",
                "readOnly": true
              }
            },
            "properties": [
              {
                "id": "custom.hideFrom",
                "value": {
                  "legend": false,
                  "tooltip": true,
                  "viz": true
                }
              }
            ]
          }
        ]
      },
      "gridPos": {
        "h": 16,
        "w": 10,
        "x": 14,
        "y": 0
      },
      "id": 3,
      "options": {
        "displayLabels": [
          "value",
          "percent"
        ],
        "legend": {
          "displayMode": "table",
          "placement": "right",
          "showLegend": true,
          "values": []
        },
        "legendOptions": {
          "position": "right",
          "showLegend": true
        },
        "orientation": "horizontal",
        "pieType": "pie",
        "reduceOptions": {
          "calcs": [
            "lastNotNull"
          ],
          "fields": "",
          "values": false
        },
        "showLegend": true,
        "sort": "desc",
        "tooltip": {
          "hideZeros": false,
          "mode": "single",
          "sort": "none"
        },
        "valueOptions": {
          "decimals": 2,
          "unit": "currencyUSD"
        }
      },
      "pluginVersion": "12.2.1",
      "targets": [
        {
          "datasource": {
            "type": "prometheus",
            "uid": "prometheus"
          },
          "editorMode": "code",
          "expr": "sum by (product) (aliyun_bill_product_cost{account=~\"$account\", product=~\"$product\", month=~\"$month\"})",
          "interval": "",
          "legendFormat": "{{product}}",
          "range": true,
          "refId": "A"
        }
      ],
      "title": "Overall Product Cost Percentage",
      "type": "piechart"
    },
    {
      "datasource": {
        "type": "prometheus",
        "uid": "prometheus"
      },
      "fieldConfig": {
        "defaults": {
          "color": {
            "mode": "palette-classic"
          },
          "custom": {
            "axisBorderShow": false,
            "axisCenteredZero": false,
            "axisColorMode": "text",
            "axisLabel": "",
            "axisPlacement": "auto",
            "fillOpacity": 80,
            "gradientMode": "hue",
            "hideFrom": {
              "legend": false,
              "tooltip": false,
              "viz": false
            },
            "lineWidth": 1,
            "scaleDistribution": {
              "type": "linear"
            },
            "thresholdsStyle": {
              "mode": "off"
            }
          },
          "mappings": [],
          "thresholds": {
            "mode": "absolute",
            "steps": [
              {
                "color": "green",
                "value": 0
              },
              {
                "color": "red",
                "value": 80
              }
            ]
          },
          "unit": "currencyUSD"
        },
        "overrides": [
          {
            "matcher": {
              "id": "byName",
              "options": "Field"
            },
            "properties": [
              {
                "id": "custom.axisPlacement",
                "value": "hidden"
              }
            ]
          },
          {
            "matcher": {
              "id": "byName",
              "options": "Field"
            },
            "properties": [
              {
                "id": "custom.axisPlacement",
                "value": "hidden"
              }
            ]
          },
          {
            "matcher": {
              "id": "byName",
              "options": "Field"
            },
            "properties": [
              {
                "id": "custom.axisPlacement",
                "value": "hidden"
              }
            ]
          },
          {
            "matcher": {
              "id": "byName",
              "options": "Field"
            },
            "properties": [
              {
                "id": "custom.axisPlacement",
                "value": "hidden"
              }
            ]
          },
          {
            "matcher": {
              "id": "byName",
              "options": "Field"
            },
            "properties": [
              {
                "id": "custom.axisPlacement",
                "value": "hidden"
              }
            ]
          },
          {
            "matcher": {
              "id": "byName",
              "options": "Field"
            },
            "properties": [
              {
                "id": "custom.axisPlacement",
                "value": "hidden"
              }
            ]
          },
          {
            "matcher": {
              "id": "byName",
              "options": "Field"
            },
            "properties": [
              {
                "id": "custom.axisPlacement",
                "value": "hidden"
              }
            ]
          }
        ]
      },
      "gridPos": {
        "h": 8,
        "w": 14,
        "x": 0,
        "y": 8
      },
      "id": 2,
      "options": {
        "barRadius": 0,
        "barWidth": 0.42,
        "colorByField": "Field",
        "fullHighlight": false,
        "groupWidth": 0.75,
        "legend": {
          "alignAsTable": true,
          "calcs": [],
          "displayMode": "list",
          "placement": "right",
          "show": true,
          "showLegend": true
        },
        "orientation": "auto",
        "showValue": "auto",
        "stacking": "none",
        "tooltip": {
          "hideZeros": false,
          "mode": "single",
          "shared": true,
          "sort": "none"
        },
        "xField": "Field",
        "xTickLabelRotation": 0,
        "xTickLabelSpacing": 0
      },
      "pluginVersion": "12.2.1",
      "targets": [
        {
          "datasource": {
            "type": "prometheus",
            "uid": "prometheus"
          },
          "editorMode": "code",
          "expr": "sum by (month) (aliyun_bill_total_cost{account=~\"$account\",month=~\"$month\"})",
          "legendFormat": "{{month}} all amount",
          "range": true,
          "refId": "A"
        }
      ],
      "title": "Monthly Total Bill Amount",
      "transformations": [
        {
          "id": "reduce",
          "options": {
            "reducers": [
              "median"
            ]
          }
        },
        {
          "id": "transpose",
          "options": {}
        }
      ],
      "type": "barchart"
    },
    {
      "datasource": {
        "type": "prometheus",
        "uid": "prometheus"
      },
      "fieldConfig": {
        "defaults": {
          "color": {
            "mode": "palette-classic"
          },
          "custom": {
            "axisBorderShow": false,
            "axisCenteredZero": false,
            "axisColorMode": "text",
            "axisLabel": "",
            "axisPlacement": "auto",
            "axisSoftMax": -1,
            "fillOpacity": 99,
            "gradientMode": "hue",
            "hideFrom": {
              "legend": false,
              "tooltip": false,
              "viz": false
            },
            "lineWidth": 7,
            "scaleDistribution": {
              "type": "linear"
            },
            "thresholdsStyle": {
              "mode": "off"
            }
          },
          "mappings": [],
          "thresholds": {
            "mode": "absolute",
            "steps": [
              {
                "color": "green",
                "value": 0
              },
              {
                "color": "red",
                "value": 80
              }
            ]
          }
        },
        "overrides": []
      },
      "gridPos": {
        "h": 8,
        "w": 14,
        "x": 0,
        "y": 16
      },
      "id": 5,
      "options": {
        "barRadius": 0,
        "barWidth": 0.46,
        "fullHighlight": false,
        "groupWidth": 0.98,
        "legend": {
          "calcs": [],
          "displayMode": "list",
          "placement": "right",
          "showLegend": true
        },
        "orientation": "auto",
        "showValue": "always",
        "stacking": "none",
        "tooltip": {
          "hideZeros": false,
          "mode": "single",
          "sort": "none"
        },
        "xField": "Field",
        "xTickLabelRotation": 0,
        "xTickLabelSpacing": 0
      },
      "pluginVersion": "12.2.1",
      "targets": [
        {
          "editorMode": "code",
          "expr": "sum by (month, type) (\r\n  aliyun_bill_product_billing_type_cost{\r\n    account=~\"$account\",\r\n    product=~\"$product\",\r\n    month=~\"$month\",\r\n    type != \"others\"\r\n  }\r\n) > 0",
          "legendFormat": "{{type}}",
          "range": true,
          "refId": "A"
        },
        {
          "datasource": {
            "type": "prometheus",
            "uid": "prometheus"
          },
          "editorMode": "code",
          "expr": "sum by (month, type) (\r\n  aliyun_bill_product_billing_type_cost{\r\n    account=~\"$account\",\r\n    product=~\"$product\",\r\n    month=~\"$month\",\r\n    type = \"others\"\r\n  }\r\n)",
          "hide": false,
          "instant": false,
          "legendFormat": "Refound",
          "range": true,
          "refId": "B"
        }
      ],
      "title": "Monthly Amount Of Different Paid Type",
      "transformations": [
        {
          "id": "reduce",
          "options": {
            "reducers": [
              "lastNotNull"
            ]
          }
        },
        {
          "id": "transpose",
          "options": {}
        }
      ],
      "type": "barchart"
    },
    {
      "datasource": {
        "type": "prometheus",
        "uid": "prometheus"
      },
      "fieldConfig": {
        "defaults": {
          "color": {
            "mode": "palette-classic"
          },
          "custom": {
            "hideFrom": {
              "legend": false,
              "tooltip": false,
              "viz": false
            }
          },
          "mappings": []
        },
        "overrides": []
      },
      "gridPos": {
        "h": 8,
        "w": 10,
        "x": 14,
        "y": 16
      },
      "id": 6,
      "options": {
        "displayLabels": [
          "name",
          "percent"
        ],
        "legend": {
          "displayMode": "table",
          "placement": "right",
          "showLegend": true,
          "values": []
        },
        "pieType": "pie",
        "reduceOptions": {
          "calcs": [
            "lastNotNull"
          ],
          "fields": "",
          "values": false
        },
        "sort": "desc",
        "tooltip": {
          "hideZeros": false,
          "mode": "single",
          "sort": "none"
        }
      },
      "pluginVersion": "12.2.1",
      "targets": [
        {
          "editorMode": "code",
          "expr": "sum by (type) (aliyun_bill_product_billing_type_cost{account=~\"$account\", product=~\"$product\", month=~\"$month\"})",
          "legendFormat": "{{type}}",
          "range": true,
          "refId": "A"
        }
      ],
      "title": "Percent Of Diferent Paid Type",
      "type": "piechart"
    },
    {
      "datasource": {
        "type": "prometheus",
        "uid": "prometheus"
      },
      "fieldConfig": {
        "defaults": {
          "color": {
            "mode": "palette-classic"
          },
          "custom": {
            "axisBorderShow": false,
            "axisCenteredZero": false,
            "axisColorMode": "text",
            "axisLabel": "",
            "axisPlacement": "auto",
            "fillOpacity": 45,
            "gradientMode": "hue",
            "hideFrom": {
              "legend": false,
              "tooltip": false,
              "viz": false
            },
            "lineWidth": 3,
            "scaleDistribution": {
              "type": "linear"
            },
            "thresholdsStyle": {
              "mode": "off"
            }
          },
          "mappings": [],
          "thresholds": {
            "mode": "absolute",
            "steps": [
              {
                "color": "green",
                "value": 0
              },
              {
                "color": "red",
                "value": 80
              }
            ]
          },
          "unit": "currencyUSD"
        },
        "overrides": [
          {
            "matcher": {
              "id": "byName",
              "options": "Field"
            },
            "properties": [
              {
                "id": "custom.axisPlacement",
                "value": "hidden"
              }
            ]
          },
          {
            "matcher": {
              "id": "byName",
              "options": "Field"
            },
            "properties": [
              {
                "id": "custom.axisPlacement",
                "value": "hidden"
              }
            ]
          },
          {
            "matcher": {
              "id": "byName",
              "options": "Field"
            },
            "properties": [
              {
                "id": "custom.axisPlacement",
                "value": "hidden"
              }
            ]
          },
          {
            "matcher": {
              "id": "byName",
              "options": "Field"
            },
            "properties": [
              {
                "id": "custom.axisPlacement",
                "value": "hidden"
              }
            ]
          },
          {
            "matcher": {
              "id": "byName",
              "options": "Field"
            },
            "properties": [
              {
                "id": "custom.axisPlacement",
                "value": "hidden"
              }
            ]
          },
          {
            "matcher": {
              "id": "byName",
              "options": "Field"
            },
            "properties": [
              {
                "id": "custom.axisPlacement",
                "value": "hidden"
              }
            ]
          },
          {
            "matcher": {
              "id": "byName",
              "options": "Field"
            },
            "properties": [
              {
                "id": "custom.axisPlacement",
                "value": "hidden"
              }
            ]
          }
        ]
      },
      "gridPos": {
        "h": 9,
        "w": 24,
        "x": 0,
        "y": 24
      },
      "id": 1,
      "options": {
        "barRadius": 0,
        "barWidth": 0.97,
        "fullHighlight": false,
        "groupWidth": 1,
        "legend": {
          "alignAsTable": true,
          "calcs": [],
          "displayMode": "list",
          "placement": "right",
          "show": true,
          "showLegend": true
        },
        "orientation": "auto",
        "showValue": "auto",
        "stacking": "none",
        "tooltip": {
          "hideZeros": false,
          "mode": "single",
          "shared": true,
          "sort": "none"
        },
        "xField": "Field",
        "xTickLabelRotation": 0,
        "xTickLabelSpacing": 0
      },
      "pluginVersion": "12.2.1",
      "targets": [
        {
          "datasource": {
            "type": "prometheus",
            "uid": "prometheus"
          },
          "editorMode": "code",
          "expr": "sum by (month, product) (aliyun_bill_product_cost{account=~\"$account\", month=~\"$month\"} > 49.99)",
          "legendFormat": "{{product}}",
          "range": true,
          "refId": "A"
        },
        {
          "datasource": {
            "type": "prometheus",
            "uid": "prometheus"
          },
          "editorMode": "code",
          "expr": "sum by (month) (aliyun_bill_product_cost{account=~\"$account\", month=~\"$month\"} < 50)",
          "legendFormat": "Other",
          "range": true,
          "refId": "B"
        },
        {
          "datasource": {
            "type": "prometheus",
            "uid": "prometheus"
          },
          "expr": "",
          "hide": false,
          "instant": false,
          "range": true,
          "refId": "C"
        }
      ],
      "title": "Monthly Product Cost Breakdown (Other < $50)",
      "transformations": [
        {
          "id": "reduce",
          "options": {
            "reducers": [
              "mean"
            ]
          }
        },
        {
          "id": "transpose",
          "options": {}
        }
      ],
      "type": "barchart"
    }
  ],
  "preload": false,
  "refresh": "5m",
  "schemaVersion": 42,
  "tags": [],
  "templating": {
    "list": [
      {
        "allValue": ".*",
        "current": {
          "text": [
            "ltex"
          ],
          "value": [
            "ltex"
          ]
        },
        "datasource": "Prometheus",
        "includeAll": true,
        "label": "Account",
        "multi": true,
        "name": "account",
        "options": [],
        "query": "label_values(aliyun_bill_total_cost, account)",
        "refresh": 1,
        "type": "query"
      },
      {
        "allValue": ".*",
        "current": {
          "text": [
            "2025-11"
          ],
          "value": [
            "2025-11"
          ]
        },
        "datasource": "Prometheus",
        "includeAll": true,
        "label": "Month (月份)",
        "multi": true,
        "name": "month",
        "options": [],
        "query": "label_values(aliyun_bill_total_cost, month)",
        "refresh": 1,
        "type": "query"
      },
      {
        "allValue": ".*",
        "current": {
          "text": "All",
          "value": [
            "$__all"
          ]
        },
        "datasource": "Prometheus",
        "includeAll": true,
        "label": "Service Type",
        "multi": true,
        "name": "product",
        "options": [],
        "query": "label_values(aliyun_bill_product_cost, product)",
        "refresh": 1,
        "type": "query"
      }
    ]
  },
  "time": {
    "from": "now-6h",
    "to": "now"
  },
  "timepicker": {},
  "timezone": "browser",
  "title": "Aliyun Billing Dashboard",
  "uid": "aliyun_billing_analysis",
  "version": 61
}
